odoo/addons/account_move_line_auto_reconcile_hook/README.rst
odoo/addons/account_move_line_auto_reconcile_hook/__init__.py
odoo/addons/account_move_line_auto_reconcile_hook/__manifest__.py
odoo/addons/account_move_line_auto_reconcile_hook/hooks.py
odoo/addons/account_move_line_auto_reconcile_hook/i18n/account_move_line_auto_reconcile_hook.pot
odoo/addons/account_move_line_auto_reconcile_hook/models/__init__.py
odoo/addons/account_move_line_auto_reconcile_hook/models/account_move_line.py
odoo/addons/account_move_line_auto_reconcile_hook/readme/CONTRIBUTORS.rst
odoo/addons/account_move_line_auto_reconcile_hook/readme/DESCRIPTION.rst
odoo/addons/account_move_line_auto_reconcile_hook/readme/USAGE.rst
odoo/addons/account_move_line_auto_reconcile_hook/static/description/icon.png
odoo/addons/account_move_line_auto_reconcile_hook/static/description/index.html
odoo11_addon_account_move_line_auto_reconcile_hook-11.0.1.0.0.99.dev3.dist-info/METADATA
odoo11_addon_account_move_line_auto_reconcile_hook-11.0.1.0.0.99.dev3.dist-info/WHEEL
odoo11_addon_account_move_line_auto_reconcile_hook-11.0.1.0.0.99.dev3.dist-info/top_level.txt
odoo11_addon_account_move_line_auto_reconcile_hook-11.0.1.0.0.99.dev3.dist-info/RECORD
